assert_json_schema/__init__.py
assert_json_schema/assert_schema.py
assert_json_schema-0.1.2.dist-info/LICENSE
assert_json_schema-0.1.2.dist-info/WHEEL
assert_json_schema-0.1.2.dist-info/METADATA
assert_json_schema-0.1.2.dist-info/RECORD
